django_auth_dingding/__init__.py
django_auth_dingding/apps.py
django_auth_dingding/auth.py
django_auth_dingding/models.py
django_auth_dingding/tests.py
django_auth_dingding/urls.py
django_auth_dingding/utils.py
django_auth_dingding/views.py
django_auth_dingding-0.0.3.dist-info/LICENSE
django_auth_dingding-0.0.3.dist-info/METADATA
django_auth_dingding-0.0.3.dist-info/WHEEL
django_auth_dingding-0.0.3.dist-info/top_level.txt
django_auth_dingding-0.0.3.dist-info/RECORD
