Metadata-Version: 2.1
Name: django-auth-dingding
Version: 0.0.3
Summary: A simple Dingding auth Django app.
Author-email: quanbisen <1769128867@qq.com>
Project-URL: Homepage, https://github.com/quanbisen/django-dingding-auth
Project-URL: Bug Tracker, https://github.com/quanbisen/django-dingding-auth/issues
Classifier: Programming Language :: Python :: 3
Classifier: License :: OSI Approved :: MIT License
Classifier: Operating System :: OS Independent
Requires-Python: >=3.7
License-File: LICENSE
